<?xml version="1.0" encoding="utf-8"?><toc><breadcrumbs><li><a href="f7be9efe-49d9-5557-f7a7-7f5766fab7f4.htm">Docs</a></li><li><a href="f7be9efe-49d9-5557-f7a7-7f5766fab7f4.htm">3CX Phone System Object Model v<wbr />4.<wbr />0.<wbr />0.<wbr />0 V<wbr />20</a></li><li><a href="e7895130-35e8-49f4-2cef-6a1a2a1b8364.htm">Call<wbr />Flow</a></li></breadcrumbs><tocItems><li><a id="26af7001-574d-f2a7-4096-43303a69e4bf" class="has-submenu" href="26af7001-574d-f2a7-4096-43303a69e4bf.htm"><span data-tocFile="../toc/IDAAA.xml" class="icon toggle" onclick="ToggleExpandCollapse(this); return false;"><i class="fa fa-angle-right"> </i></span>Common<wbr />Routing<wbr />Extensions</a><ul class="toc-menu is-hidden"> </ul></li><li><a id="2c2d307d-cdc7-8ac7-87a2-49df53623c5a" class="has-submenu" href="2c2d307d-cdc7-8ac7-87a2-49df53623c5a.htm"><span data-tocFile="../toc/IDBAA.xml" class="icon toggle" onclick="ToggleExpandCollapse(this); return false;"><i class="fa fa-angle-right"> </i></span>ICall</a><ul class="toc-menu is-hidden"> </ul></li><li><a id="a0a2c22e-9e9a-087a-90d2-65b16264eb64" class="has-submenu" href="a0a2c22e-9e9a-087a-90d2-65b16264eb64.htm"><span data-tocFile="../toc/IDCAA.xml" class="icon toggle" onclick="ToggleExpandCollapse(this); return false;"><i class="fa fa-angle-right"> </i></span>ICaller<wbr />Info</a><ul class="toc-menu is-hidden"> </ul></li><li><a id="4bdd662a-0698-c6fa-416d-7c6171d4caaf" class="has-submenu" href="4bdd662a-0698-c6fa-416d-7c6171d4caaf.htm"><span data-tocFile="../toc/IDDAA.xml" class="icon toggle" onclick="ToggleExpandCollapse(this); return false;"><i class="fa fa-angle-right"> </i></span>ICall<wbr />Handler</a><ul class="toc-menu is-hidden"> </ul></li><li><a id="0b714b16-6fcb-473f-8e1a-90f875188fc2" class="has-submenu" href="0b714b16-6fcb-473f-8e1a-90f875188fc2.htm"><span data-tocFile="../toc/IDEAA.xml" class="icon toggle" onclick="ToggleExpandCollapse(this); return false;"><i class="fa fa-angle-right"> </i></span>ICall<wbr />Handler<wbr />Ex</a><ul class="toc-menu is-hidden"> </ul></li><li><a id="122ca9f8-0c29-9a8a-88a8-5ca6db275713" href="122ca9f8-0c29-9a8a-88a8-5ca6db275713.htm">Local<wbr />Recording<wbr />State</a></li><li><a id="96a440f2-31c0-d37e-df59-92839aa554e8" href="96a440f2-31c0-d37e-df59-92839aa554e8.htm">Play<wbr />Prompt<wbr />Options</a></li><li><a id="3be85bf0-7988-4e9d-e17d-9676542e2efd" href="3be85bf0-7988-4e9d-e17d-9676542e2efd.htm">Record<wbr />Direction</a></li><li><a id="3ca7cf40-397d-4fa3-21e2-cffe2844d6bf" class="has-submenu" href="3ca7cf40-397d-4fa3-21e2-cffe2844d6bf.htm"><span data-tocFile="../toc/IDIAA.xml" class="icon toggle" onclick="ToggleExpandCollapse(this); return false;"><i class="fa fa-angle-right"> </i></span>Script<wbr />Base&lt;T&gt;</a><ul class="toc-menu is-hidden"> </ul></li><li><a id="55536478-f87c-13de-f8aa-ef1d09c7c145" href="55536478-f87c-13de-f8aa-ef1d09c7c145.htm">Script<wbr />Execution<wbr />Mode</a></li><li><a id="17ff9873-360a-190b-8111-4e83f6f5e5a7" class="has-submenu" href="17ff9873-360a-190b-8111-4e83f6f5e5a7.htm"><span data-tocFile="../toc/IDKAA.xml" class="icon toggle" onclick="ToggleExpandCollapse(this); return false;"><i class="fa fa-angle-right"> </i></span>Time<wbr />Based<wbr />Destination</a><ul class="toc-menu is-hidden"> </ul></li></tocItems></toc>